LICENSE
MANIFEST.in
README.rst
VERSION
requirements.txt
setup.py
src/cdumay_error/__init__.py
src/cdumay_error/registry.py
src/cdumay_error/types.py
src/cdumay_error.egg-info/PKG-INFO
src/cdumay_error.egg-info/SOURCES.txt
src/cdumay_error.egg-info/dependency_links.txt
src/cdumay_error.egg-info/requires.txt
src/cdumay_error.egg-info/top_level.txt
src/cdumay_error.egg-info/zip-safe