Metadata-Version: 2.1
Name: cdumay-error
Version: 0.2.1
Summary: Generic error library
Home-page: https://github.com/cdumay/cdumay-error
Author: Cedric DUMAY
Author-email: cedric.dumay@gmail.com
License: BSD 3-Clause
Platform: UNKNOWN
Classifier: Programming Language :: Python
Provides-Extra: tests
License-File: LICENSE
